queryS3/QS3.py
queryS3/__init__.py
queryS3/app.py
queryS3-0.0.19.dist-info/LICENSE
queryS3-0.0.19.dist-info/METADATA
queryS3-0.0.19.dist-info/WHEEL
queryS3-0.0.19.dist-info/top_level.txt
queryS3-0.0.19.dist-info/RECORD
