Metadata-Version: 2.1
Name: queryS3
Version: 0.0.19
Summary: Minimum version of query s3 by label
Home-page: https://github.com/eugenechang2002/AITestResourceLibrary
Author: Qiao Liu, Everette Li
Author-email: qiao.liu01@sjsu.edu, everetteli12@gmail.com
License: UNKNOWN
Platform: UNKNOWN
Classifier: Programming Language :: Python :: 3
Classifier: License :: OSI Approved :: MIT License
Classifier: Operating System :: OS Independent
Requires-Python: >=2.0
Requires-Dist: pandas
Requires-Dist: nltk
